doml_synthesis/__init__.py
doml_synthesis/__main__.py
doml_synthesis/data.py
doml_synthesis/requirements.py
doml_synthesis/results.py
doml_synthesis/solver.py
doml_synthesis/synthesis.py
doml_synthesis/tests.py
doml_synthesis/types.py
piacere_doml_synthesis-2023.1.3.dist-info/METADATA
piacere_doml_synthesis-2023.1.3.dist-info/WHEEL
piacere_doml_synthesis-2023.1.3.dist-info/top_level.txt
piacere_doml_synthesis-2023.1.3.dist-info/RECORD
