Metadata-Version: 2.1
Name: piacere-doml-synthesis
Version: 2023.1.3
Summary: Synthetize DOML from user requirements
Author-email: Andrea Franchini <hello@andreafranchini.com>
License: MIT License
Project-URL: homepage, https://github.com/andreafra/piacere-synthesis
Project-URL: documentation, https://piacere-model-checker.readthedocs.org
Project-URL: repository, https://github.com/andreafra/piacere-synthesis.git
Keywords: z3,synthesis,doml,piacere
Classifier: Development Status :: 4 - Beta
Classifier: Programming Language :: Python
Requires-Dist: PyYAML
Requires-Dist: z3-solver
Requires-Dist: termcolor
